[{"district":"Moyamba","product":"Rice","price":1000},{"district":"Kono","product":"orange","price":16},{"district":"Karene","product":"Maize","price":10},{"district":"Kono","product":"kola","price":3},{"district":"Bo","product":"kola","price":6},{"district":"LO","product":"fish","price":5},{"district":"Bonth","product":"maize","price":10},{"district":"KENEMEA","product":"Orange","price":12},{"district":"BOMBALI","product":"Cassava","price":10},{"district":"KENEMEA","product":"COCOA","price":30},{"district":"BO","product":"GARI","price":10},{"district":"FALABA","product":"MANGO","price":20},{"district":"KENEMA","product":"BANANA","price":25},{"district":"BONTH","product":"APPLE","price":15}]